contenda_api_client/__init__.py
contenda_api_client/api/__init__.py
contenda_api_client/api/content_and_results/__init__.py
contenda_api_client/api/content_and_results/get_all_blog_images_api_v2_content_blog_blog_id_images_get.py
contenda_api_client/api/content_and_results/get_blog_result_document_api_v2_content_blog_blog_id_get.py
contenda_api_client/api/content_and_results/get_blog_result_markdown_api_v2_content_blog_blog_id_markdown_get.py
contenda_api_client/api/content_and_results/get_regeneration_feedback_options_api_v2_content_blog_segment_revision_feedback_options_get.py
contenda_api_client/api/content_and_results/get_segment_transcript_api_v2_content_blog_segment_segment_id_transcript_get.py
contenda_api_client/api/content_and_results/list_blogs_api_v2_content_blog_list_get.py
contenda_api_client/api/content_and_results/save_blog_result_document_api_v2_content_blog_blog_id_put.py
contenda_api_client/api/content_and_results/save_segment_revision_feedback_api_v2_content_blog_segment_revision_feedback_revision_id_put.py
contenda_api_client/api/experimental/__init__.py
contenda_api_client/api/experimental/get_rss_feed_parsed_api_v2_blog_rss_feed_parsed_get.py
contenda_api_client/api/identity/__init__.py
contenda_api_client/api/identity/get_token_endpoint_api_v2_identity_token_post.py
contenda_api_client/api/jobs/__init__.py
contenda_api_client/api/jobs/get_job_api_v2_jobs_status_job_id_get.py
contenda_api_client/api/jobs/get_usage_api_v2_jobs_usage_limits_get.py
contenda_api_client/api/jobs/post_video_to_blog_job_api_v2_jobs_video_to_blog_post.py
contenda_api_client/api/media/__init__.py
contenda_api_client/api/media/get_media_list_api_v2_media_list_get.py
contenda_api_client/api/utility/__init__.py
contenda_api_client/api/utility/health_health_get.py
contenda_api_client/client.py
contenda_api_client/errors.py
contenda_api_client/models/__init__.py
contenda_api_client/models/blog_entry.py
contenda_api_client/models/blog_image_response_model.py
contenda_api_client-0.1.1.dist-info/WHEEL
contenda_api_client-0.1.1.dist-info/METADATA
contenda_api_client-0.1.1.dist-info/RECORD
